py21cmfish/__init__.py
py21cmfish/_version.py
py21cmfish/fishy.py
py21cmfish/io.py
py21cmfish/params.py
py21cmfish/power_spectra.py
py21cmfish/tests/__init__.py
py21cmfish/tests/conftest.py
py21cmfish/tests/test_examples.py
py21cmfish-0.1.0.dist-info/AUTHORS.rst
py21cmfish-0.1.0.dist-info/LICENSE
py21cmfish-0.1.0.dist-info/METADATA
py21cmfish-0.1.0.dist-info/WHEEL
py21cmfish-0.1.0.dist-info/entry_points.txt
py21cmfish-0.1.0.dist-info/top_level.txt
py21cmfish-0.1.0.dist-info/RECORD
