Metadata-Version: 2.1
Name: py21cmfish
Version: 0.1.0
Summary: A python package for doing Fisher matrix analyses with 21cmFAST
Home-page: https://github.com/charlottenosam/21cmfish
Author: Charlotte Mason
Author-email: charlotte.mason@cfa.harvard.edu
License: BSD (3-clause)
Platform: UNKNOWN
Classifier: Development Status :: 2 - Pre-Alpha
Classifier: Natural Language :: English
Classifier: Programming Language :: Python :: 3
Requires-Python: >=3.7
Requires-Dist: matplotlib
Requires-Dist: numpy
Requires-Dist: joblib
Requires-Dist: powerbox
